LICENSE
README.md
setup.py
newlandface_r/__init__.py
newlandface_r/nlface.py
newlandface_r.egg-info/PKG-INFO
newlandface_r.egg-info/SOURCES.txt
newlandface_r.egg-info/dependency_links.txt
newlandface_r.egg-info/requires.txt
newlandface_r.egg-info/top_level.txt
newlandface_r/basemodels/DeepID.py
newlandface_r/basemodels/DlibResNet.py
newlandface_r/basemodels/Facenet.py
newlandface_r/basemodels/FbDeepFace.py
newlandface_r/basemodels/OpenFace.py
newlandface_r/basemodels/VGGFace.py
newlandface_r/basemodels/__init__.py
newlandface_r/commons/__init__.py
newlandface_r/commons/distance.py
newlandface_r/commons/functions.py
newlandface_r/commons/realtime.py
newlandface_r/extendedmodels/Age.py
newlandface_r/extendedmodels/Emotion.py
newlandface_r/extendedmodels/Gender.py
newlandface_r/extendedmodels/Race.py
newlandface_r/extendedmodels/__init__.py
newlandface_r/models/__init__.py