Metadata-Version: 2.1
Name: newlandface-r
Version: 0.1
Summary: 修改了fjndfazp/newlandface的默认home路径问题等 
Home-page: https://github.com/krishuang2008/newlandface_r
Author: krishuang
Author-email: huangzikun2008@hotmail.com
License: UNKNOWN
Platform: UNKNOWN
Classifier: Programming Language :: Python :: 3
Classifier: License :: OSI Approved :: MIT License
Classifier: Operating System :: OS Independent
Requires-Python: >=3.5
License-File: LICENSE
